MANIFEST.in
README.md
README.rst
requirements.txt
setup.py
service_runner/__init__.py
service_runner/custom_settings_tmp.py
service_runner/manage.py
service_runner.egg-info/PKG-INFO
service_runner.egg-info/SOURCES.txt
service_runner.egg-info/dependency_links.txt
service_runner.egg-info/entry_points.txt
service_runner.egg-info/not-zip-safe
service_runner.egg-info/requires.txt
service_runner.egg-info/top_level.txt
service_runner/locale/zh-Hans/LC_MESSAGES/django.mo
service_runner/locale/zh-Hans/LC_MESSAGES/django.po
service_runner/locale/zh/LC_MESSAGES/django.mo
service_runner/locale/zh/LC_MESSAGES/django.po
service_runner/service_runner/__init__.py
service_runner/service_runner/celery_config.py
service_runner/service_runner/routing.py
service_runner/service_runner/settings.py
service_runner/service_runner/urls.py
service_runner/service_runner/wsgi.py
service_runner/service_runner/answeb/__init__.py
service_runner/service_runner/answeb/admin.py
service_runner/service_runner/answeb/ansible_api.py
service_runner/service_runner/answeb/apps.py
service_runner/service_runner/answeb/models.py
service_runner/service_runner/answeb/tests.py
service_runner/service_runner/answeb/views.py
service_runner/service_runner/answeb/migrations/__init__.py
service_runner/service_runner/answeb/playbooks/memory_cpu_diskspace_uptime.yml
service_runner/service_runner/asset/__init__.py
service_runner/service_runner/asset/admin.py
service_runner/service_runner/asset/apps.py
service_runner/service_runner/asset/consumers.py
service_runner/service_runner/asset/models.py
service_runner/service_runner/asset/routing.py
service_runner/service_runner/asset/tests.py
service_runner/service_runner/asset/utils.py
service_runner/service_runner/asset/views.py
service_runner/service_runner/asset/migrations/0001_initial.py
service_runner/service_runner/asset/migrations/0002_sshkey.py
service_runner/service_runner/asset/migrations/0003_auto_20191014_0918.py
service_runner/service_runner/asset/migrations/0004_auto_20191014_0953.py
service_runner/service_runner/asset/migrations/__init__.py
service_runner/service_runner/core/__init__.py
service_runner/service_runner/core/admin.py
service_runner/service_runner/core/apps.py
service_runner/service_runner/core/models.py
